README.rst
setup.py
symtmm/__init__.py
symtmm/backing.py
symtmm/solver.py
symtmm.egg-info/PKG-INFO
symtmm.egg-info/SOURCES.txt
symtmm.egg-info/dependency_links.txt
symtmm.egg-info/not-zip-safe
symtmm.egg-info/requires.txt
symtmm.egg-info/top_level.txt
symtmm/interfaces/__init__.py
symtmm/interfaces/interfaces.py
symtmm/interfaces/utils.py
symtmm/layers/__init__.py
symtmm/layers/fluid.py
symtmm/layers/layer.py
symtmm/layers/utils.py
symtmm/media/__init__.py
symtmm/media/air.py
symtmm/media/eqf.py
symtmm/media/medium.py