Metadata-Version: 1.1
Name: symtmm
Version: 0.0.1
Summary: Symbolic multilayer acoustic solver
Home-page: https://github.com/matael/symtmm
Author: Mathieu (matael) Gaborit
Author-email: gaborit@kth.se
License: MIT
Platform: UNKNOWN
Classifier: Programming Language :: Python :: 3
Classifier: Operating System :: OS Independent
